ycpm/__init__.py
ycpm/cli.py
ycpm/install.py
ycpm-0.1.0.dist-info/METADATA
ycpm-0.1.0.dist-info/WHEEL
ycpm-0.1.0.dist-info/entry_points.txt
ycpm-0.1.0.dist-info/top_level.txt
ycpm-0.1.0.dist-info/RECORD
