Metadata-Version: 2.4
Name: ycpm
Version: 0.1.0
Summary: Your Clyp package manager
Home-page: https://github.com/clyplang/ycpm
Author: CodeSoft
License: MIT
Project-URL: Source, https://github.com/clyplang/ycpm
Dynamic: author
Dynamic: description
Dynamic: description-content-type
Dynamic: home-page
Dynamic: license
Dynamic: project-url
Dynamic: summary
